nuclio/__init__.py
nuclio/__main__.py
nuclio/archive.py
nuclio/auth.py
nuclio/build.py
nuclio/config.py
nuclio/deploy.py
nuclio/export.py
nuclio/magic.py
nuclio/request.py
nuclio/triggers.py
nuclio/utils.py
nuclio_jupyter-0.13.0.dist-info/licenses/LICENSE.txt
nuclio_jupyter-0.13.0.dist-info/METADATA
nuclio_jupyter-0.13.0.dist-info/WHEEL
nuclio_jupyter-0.13.0.dist-info/entry_points.txt
nuclio_jupyter-0.13.0.dist-info/top_level.txt
nuclio_jupyter-0.13.0.dist-info/RECORD
