Metadata-Version: 2.4
Name: nuclio-jupyter
Version: 0.13.0
Summary: Convert Jupyter notebook to nuclio
Author: Iguazio
License-Expression: Apache-2.0
Project-URL: Homepage, https://github.com/nuclio/nuclio-jupyter
Project-URL: Repository, https://github.com/nuclio/nuclio-jupyter
Classifier: Development Status :: 4 - Beta
Classifier: Intended Audience :: Developers
Classifier: Operating System :: POSIX :: Linux
Classifier: Operating System :: Microsoft :: Windows
Classifier: Operating System :: MacOS
Classifier: Programming Language :: Python :: 3
Classifier: Programming Language :: Python :: 3.11
Classifier: Programming Language :: Python :: 3.12
Classifier: Programming Language :: Python
Classifier: Topic :: Software Development :: Libraries :: Python Modules
Classifier: Topic :: Software Development :: Libraries
Requires-Python: >=3.11
License-File: LICENSE.txt
Requires-Dist: nbconvert>=6.4.5
Requires-Dist: pyyaml<7,>=3.13
Requires-Dist: requests>=2.32.4
Requires-Dist: importlib-metadata<8.0.0
Requires-Dist: ipython>=7.27.0
Requires-Dist: ipykernel>=5.0.0
Requires-Dist: twine>=6.2.0
Requires-Dist: flake8>=7.3.0
Provides-Extra: dev
Requires-Dist: build; extra == "dev"
Requires-Dist: flake8; extra == "dev"
Requires-Dist: pytest; extra == "dev"
Requires-Dist: pyyaml; extra == "dev"
Requires-Dist: sphinx~=4.3.0; extra == "dev"
Requires-Dist: twine; extra == "dev"
Requires-Dist: wheel; extra == "dev"
Provides-Extra: boto3
Requires-Dist: boto3>=1.28.0; extra == "boto3"
Dynamic: license-file
